{"web":{"client_id":"1069346785580-k1djaegd3u62nv0smnge5oqrmg043ouh.apps.googleusercontent.com","project_id":"email-sender-441822","auth_uri":"https://accounts.google.com/o/oauth2/auth","token_uri":"https://oauth2.googleapis.com/token","auth_provider_x509_cert_url":"https://www.googleapis.com/oauth2/v1/certs","client_secret":"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","redirect_uris":["http://localhost:8080/","http://localhost:8000/","http://127.0.0.1:8000/contact/","http://localhost:52916/","http://localhost:52931/"],"javascript_origins":["http://localhost:8080","http://localhost:8000"]}}